seetrain/__init__.py
seetrain/cli.py
seetrain/env.py
seetrain/formatter.py
seetrain/setting.py
seetrain/api/__init__.py
seetrain/api/api.py
seetrain/api/types.py
seetrain/data/__init__.py
seetrain/data/data.py
seetrain/data/namer.py
seetrain/data/modules/__init__.py
seetrain/data/modules/audio/__init__.py
seetrain/data/modules/image/__init__.py
seetrain/data/modules/text/__init__.py
seetrain/data/modules/video/__init__.py
seetrain/data/run/__init__.py
seetrain/data/run/metadata/__init__.py
seetrain/data/run/metadata/conda.py
seetrain/data/run/metadata/python.py
seetrain/data/run/metadata/requirements.py
seetrain/data/run/metadata/hardware/__init__.py
seetrain/data/run/metadata/hardware/cpu.py
seetrain/data/run/metadata/hardware/disk.py
seetrain/data/run/metadata/hardware/memory.py
seetrain/data/run/metadata/hardware/network.py
seetrain/data/run/metadata/hardware/type.py
seetrain/data/run/metadata/hardware/utils.py
seetrain/data/run/metadata/hardware/gpu/metax.py
seetrain/data/run/metadata/hardware/gpu/moorethreads.py
seetrain/data/run/metadata/hardware/gpu/nvidia.py
seetrain/data/run/metadata/hardware/soc/apple.py
seetrain/integration/README.md
seetrain/integration/__init__.py
seetrain/integration/autolog.py
seetrain/integration/base.py
seetrain/integration/callback.py
seetrain/integration/converters.py
seetrain/integration/errors.py
seetrain/integration/examples.py
seetrain/integration/main.py
seetrain/integration/tracker.py
seetrain/integration/utils.py
seetrain/integration/visbackend.py
seetrain/log/__init__.py
seetrain/log/counter.py
seetrain/log/log.py
seetrain/log/profiler.py
seetrain/log/type.py
seetrain/sync/__init__.py
seetrain/sync/circuit_breaker.py
seetrain/sync/consumer.py
seetrain/sync/media_handler.py
seetrain/sync/metrics.py
seetrain/sync/qm.py
seetrain/sync/tensorboard.py
seetrain/sync/types.py
seetrain/sync/uploader.py
seetrain/sync/wandb.py
seetrain/toolkit/__init__.py
seetrain/toolkit/logger.py
seetrain/toolkit/model.py
seetrain_ml-0.1.21.dist-info/licenses/LICENSE
seetrain_ml-0.1.21.dist-info/METADATA
seetrain_ml-0.1.21.dist-info/WHEEL
seetrain_ml-0.1.21.dist-info/entry_points.txt
seetrain_ml-0.1.21.dist-info/top_level.txt
seetrain_ml-0.1.21.dist-info/RECORD
