Metadata-Version: 2.4
Name: seetrain-ml
Version: 0.1.21
Summary: 深度学习实验跟踪工具
Author-email: SeeTrain Team <seetrain@example.com>
Maintainer-email: SeeTrain Team <seetrain@example.com>
License: MIT
Project-URL: Homepage, https://github.com/seetrain/seetrain
Project-URL: Documentation, https://seetrain.readthedocs.io/
Project-URL: Repository, https://github.com/seetrain/seetrain
Project-URL: Bug Tracker, https://github.com/seetrain/seetrain/issues
Keywords: deep learning,experiment tracking,pytorch,tensorflow,keras,mlflow,wandb
Classifier: Development Status :: 3 - Alpha
Classifier: Intended Audience :: Developers
Classifier: Intended Audience :: Science/Research
Classifier: License :: OSI Approved :: MIT License
Classifier: Operating System :: OS Independent
Classifier: Programming Language :: Python :: 3
Classifier: Programming Language :: Python :: 3.8
Classifier: Programming Language :: Python :: 3.9
Classifier: Programming Language :: Python :: 3.10
Classifier: Programming Language :: Python :: 3.11
Classifier: Topic :: Scientific/Engineering :: Artificial Intelligence
Classifier: Topic :: Software Development :: Libraries :: Python Modules
Requires-Python: >=3.8
License-File: LICENSE
Requires-Dist: requests
Requires-Dist: pydantic
Requires-Dist: rich
Requires-Dist: psutil
Requires-Dist: nvidia-ml-py
Requires-Dist: pyyaml
Requires-Dist: opencv-python
Requires-Dist: numpy
Requires-Dist: importlib-metadata>=1.0; python_version < "3.8"
Provides-Extra: dev
Requires-Dist: pytest>=6.0; extra == "dev"
Requires-Dist: pytest-cov; extra == "dev"
Requires-Dist: black; extra == "dev"
Requires-Dist: flake8; extra == "dev"
Requires-Dist: mypy; extra == "dev"
Provides-Extra: docs
Requires-Dist: sphinx; extra == "docs"
Requires-Dist: sphinx-rtd-theme; extra == "docs"
Requires-Dist: myst-parser; extra == "docs"
Dynamic: license-file
